README.md
setup.py
recollect_waste/__init__.py
recollect_waste.egg-info/PKG-INFO
recollect_waste.egg-info/SOURCES.txt
recollect_waste.egg-info/dependency_links.txt
recollect_waste.egg-info/requires.txt
recollect_waste.egg-info/top_level.txt